<?xml version="1.0"?>
<!-- edited with XMLSpy v2014 rel. 2 sp1 (http://www.altova.com) by Soren Johnson (private) -->
<Root>
	<Entry>
		<zType>HQLEVEL_0</zType>
		<Name>TEXT_HQLEVEL_0</Name>
		<zFoleySound/>
		<iUpgradeClaims/>
		<HandicapUpgradeClaims/>
	</Entry>
	<Entry>
		<zType>HQLEVEL_1</zType>
		<Name>TEXT_HQLEVEL_1</Name>
		<zFoleySound/>
		<iUpgradeClaims/>
		<HandicapUpgradeClaims/>
	</Entry>
	<Entry>
		<zType>HQLEVEL_2</zType>
		<Name>TEXT_HQLEVEL_2</Name>
		<zFoleySound>AUDIO_HQ_UPGRADE_FOLEY_2</zFoleySound>
		<iUpgradeClaims>3</iUpgradeClaims>
		<HandicapUpgradeClaims>
			<Pair>
				<zIndex>HANDICAP_APPLICANT</zIndex>
				<iValue>1</iValue>
			</Pair>
			<Pair>
				<zIndex>HANDICAP_INTERN</zIndex>
				<iValue>1</iValue>
			</Pair>
			<Pair>
				<zIndex>HANDICAP_ASSISTANT</zIndex>
				<iValue>1</iValue>
			</Pair>
			<Pair>
				<zIndex>HANDICAP_EMPLOYEE</zIndex>
				<iValue>1</iValue>
			</Pair>
			<Pair>
				<zIndex>HANDICAP_GURU</zIndex>
				<iValue>-1</iValue>
			</Pair>
		</HandicapUpgradeClaims>
	</Entry>
	<Entry>
		<zType>HQLEVEL_3</zType>
		<Name>TEXT_HQLEVEL_3</Name>
		<zFoleySound>AUDIO_HQ_UPGRADE_FOLEY_3</zFoleySound>
		<iUpgradeClaims>3</iUpgradeClaims>
		<HandicapUpgradeClaims>
			<Pair>
				<zIndex>HANDICAP_APPLICANT</zIndex>
				<iValue>1</iValue>
			</Pair>
			<Pair>
				<zIndex>HANDICAP_INTERN</zIndex>
				<iValue>1</iValue>
			</Pair>
			<Pair>
				<zIndex>HANDICAP_ASSISTANT</zIndex>
				<iValue>1</iValue>
			</Pair>
			<Pair>
				<zIndex>HANDICAP_CEO</zIndex>
				<iValue>-1</iValue>
			</Pair>
			<Pair>
				<zIndex>HANDICAP_GURU</zIndex>
				<iValue>-1</iValue>
			</Pair>
		</HandicapUpgradeClaims>
	</Entry>
	<Entry>
		<zType>HQLEVEL_4</zType>
		<Name>TEXT_HQLEVEL_4</Name>
		<zFoleySound>AUDIO_HQ_UPGRADE_FOLEY_4</zFoleySound>
		<iUpgradeClaims>4</iUpgradeClaims>
		<HandicapUpgradeClaims>
			<Pair>
				<zIndex>HANDICAP_APPLICANT</zIndex>
				<iValue>1</iValue>
			</Pair>
			<Pair>
				<zIndex>HANDICAP_INTERN</zIndex>
				<iValue>1</iValue>
			</Pair>
			<Pair>
				<zIndex>HANDICAP_VICE_PRESIDENT</zIndex>
				<iValue>-1</iValue>
			</Pair>
			<Pair>
				<zIndex>HANDICAP_CEO</zIndex>
				<iValue>-1</iValue>
			</Pair>
			<Pair>
				<zIndex>HANDICAP_GURU</zIndex>
				<iValue>-1</iValue>
			</Pair>
		</HandicapUpgradeClaims>
	</Entry>
	<Entry>
		<zType>HQLEVEL_5</zType>
		<Name>TEXT_HQLEVEL_5</Name>
		<zFoleySound>AUDIO_HQ_UPGRADE_FOLEY_5</zFoleySound>
		<iUpgradeClaims>5</iUpgradeClaims>
		<HandicapUpgradeClaims>
			<Pair>
				<zIndex>HANDICAP_APPLICANT</zIndex>
				<iValue>1</iValue>
			</Pair>
			<Pair>
				<zIndex>HANDICAP_EXECUTIVE</zIndex>
				<iValue>-1</iValue>
			</Pair>
			<Pair>
				<zIndex>HANDICAP_VICE_PRESIDENT</zIndex>
				<iValue>-1</iValue>
			</Pair>
			<Pair>
				<zIndex>HANDICAP_CEO</zIndex>
				<iValue>-1</iValue>
			</Pair>
			<Pair>
				<zIndex>HANDICAP_GURU</zIndex>
				<iValue>-1</iValue>
			</Pair>
		</HandicapUpgradeClaims>
	</Entry>
</Root>
